decoder_24.v
 //-----------------------------------------------------
 // Design Name : 2-to-4 decoder
 // File Name   : decoder.v
 // Function    : decoder using Logic Gates
 // Coder       : Watchanan Chantapakul
 // Date 		: October 8, 2015
 //-----------------------------------------------------
 
module decoder_24 (
	dout_3, dout_2, dout_1, dout_0,
	d_en,
	din_1, din_0
);

	input d_en, din_1, din_0;
	output dout_3, dout_2, dout_1, dout_0;
	wire w_not1, w_not0;

	not not0 (w_not0, din_0);
	not not1 (w_not1, din_1);
	and and0 (dout_0, d_en, w_not1, w_not0);
	and and1 (dout_1, d_en, w_not1, din_0);
	and and2 (dout_2, d_en, din_1, w_not0);
	and and3 (dout_3, d_en, din_1, din_0);

endmodule

decoder_stimulus.v
 //-----------------------------------------------------
 // Design Name : decoder stimulus
 // File Name   : decoder_stimulus.v
 // Function    : decoder stimulus block for test bench
 // Coder       : Watchanan Chantapakul
 // Date 		: October 8, 2015
 //-----------------------------------------------------
 
 module decoder_stimulus;
 
	reg d_en;
	reg din_1, din_0;
	wire dout_3, dout_2, dout_1, dout_0;
	
	decoder_24 decoder_24_for_stimulus (dout_3, dout_2, dout_1, dout_0, d_en, din_1, din_0);
	
	initial
		begin
			$dumpfile("DecoderTimeDiagram.vcd");
			$dumpvars(0,decoder_stimulus);
			d_en = 1'b0;
			din_1 = 1'b0;
			din_0 = 1'b0;
		end
		
	always
		#5 din_0 = ~din_0;
	always
		#10 din_1 = ~din_1;
	always
		#20 d_en = ~d_en;
	initial
		begin
			#35 $finish;
		end
	
	initial
		$monitor ($time, "# Output d_en=%d | din_1=%d din_0=%d | dout_3=%d dout_2=%d dout_1=%d dout_0=%d", d_en, din_1, din_0, dout_3, dout_2, dout_1, dout_0);
 
 endmodule

DecoderTimeDiagram.vcd
$date
	Thu Oct 08 19:57:32 2015
$end
$version
	Icarus Verilog
$end
$timescale
	1s
$end
$scope module decoder_stimulus $end
$var wire 1 ! dout_3 $end
$var wire 1 " dout_2 $end
$var wire 1 # dout_1 $end
$var wire 1 $ dout_0 $end
$var reg 1 % d_en $end
$var reg 1 & din_0 $end
$var reg 1 ' din_1 $end
$scope module decoder_24_for_stimulus $end
$var wire 1 % d_en $end
$var wire 1 & din_0 $end
$var wire 1 ' din_1 $end
$var wire 1 $ dout_0 $end
$var wire 1 # dout_1 $end
$var wire 1 " dout_2 $end
$var wire 1 ! dout_3 $end
$var wire 1 ( w_not0 $end
$var wire 1 ) w_not1 $end
$upscope $end
$upscope $end
$enddefinitions $end
#0
$dumpvars
1)
1(
0'
0&
0%
0$
0#
0"
0!
$end
#5
0(
1&
#10
1(
0)
0&
1'
#15
0(
1&
#20
1$
1(
1)
0&
0'
1%
#25
0$
0(
1#
1&
#30
1"
1(
0#
0)
0&
1'
#35
0"
0(
1!
1&
